<?xml version="1.0" encoding="UTF-8"?>
<infinispan xmlns="urn:infinispan:config:6.0" xmlns:xsi="http://www.w3.org/2001/XMLSchema-instance"
	xmlns:jdbc="urn:infinispan:config:jdbc:6.0"
	xsi:schemaLocation="urn:infinispan:config:6.2 infinispan-config-6.0.xsd 
	urn:infinispan:config:jdbc:6.0 infinispan-cachestore-jdbc-config-6.0.xsd">


	<namedCache name="event">
		<eviction strategy="LRU" maxEntries="50"  />
		<indexing enabled="true" indexLocalOnly="true" >
			<properties>
				<property name="default.directory_provider" value="filesystem" />
				<property name="default.indexBase" value="ispn_index" />
			</properties>
		</indexing>
		<persistence >
			<jdbc:mixedKeyedJdbcStore xmlns="urn:infinispan:config:jdbc:6.0" preload="true">
				<jdbc:connectionPool connectionUrl="jdbc:h2:tcp://localhost:8643/eventDB"
					driverClass="org.h2.Driver" username="sa" password="" />
				<jdbc:binaryKeyedTable prefix="ISPN_MIX_BKT">
					<jdbc:idColumn name="id" type="VARCHAR" />
					<jdbc:dataColumn name="datum" type="BINARY" />
					<jdbc:timestampColumn name="version" type="BIGINT" />
				</jdbc:binaryKeyedTable>
				<jdbc:stringKeyedTable prefix="ISPN_MIX_STR" >
					<jdbc:idColumn name="id" type="VARCHAR" />
					<jdbc:dataColumn name="datum" type="BINARY" />
					<jdbc:timestampColumn name="version" type="BIGINT" />
				</jdbc:stringKeyedTable>
			</jdbc:mixedKeyedJdbcStore>
		</persistence>
	</namedCache>
	<namedCache name="metric">
		<transaction transactionMode="TRANSACTIONAL" lockingMode="PESSIMISTIC" />
	</namedCache>
</infinispan>